_DP.cpython-313-x86_64-linux-musl.so
cbayesian.cpython-313-x86_64-linux-musl.so
cimage.cpython-313-x86_64-linux-musl.so
crbfgs.cpython-313-x86_64-linux-musl.so
fpls_warp.cpython-313-x86_64-linux-musl.so
mlogit_warp.cpython-313-x86_64-linux-musl.so
oclogit_warp.cpython-313-x86_64-linux-musl.so
ocmlogit_warp.cpython-313-x86_64-linux-musl.so
optimum_reparamN2.cpython-313-x86_64-linux-musl.so
optimum_reparam_N.cpython-313-x86_64-linux-musl.so
fdasrsf/PPD.py
fdasrsf/__init__.py
fdasrsf/_distributor_init.py
fdasrsf/bayesian_functions.py
fdasrsf/boxplots.py
fdasrsf/curve_functions.py
fdasrsf/curve_pcr_regression.py
fdasrsf/curve_regression.py
fdasrsf/curve_stats.py
fdasrsf/elastic_changepoint.py
fdasrsf/elastic_glm_regression.py
fdasrsf/fPCA.py
fdasrsf/fPLS.py
fdasrsf/fPNS.py
fdasrsf/geodesic.py
fdasrsf/geometry.py
fdasrsf/gp.py
fdasrsf/image.py
fdasrsf/image_functions.py
fdasrsf/interparc.py
fdasrsf/kmeans.py
fdasrsf/pcr_regression.py
fdasrsf/plot_style.py
fdasrsf/pns.py
fdasrsf/rbfgs.py
fdasrsf/regression.py
fdasrsf/time_warping.py
fdasrsf/tolerance.py
fdasrsf/umap_metric.py
fdasrsf/utility_functions.py
fdasrsf-2.6.7.data/scripts/ex_srsf_align.py
fdasrsf.libs/libgcc_s-0cd532bd.so.1
fdasrsf.libs/libstdc++-5d72f927.so.6.0.33
fdasrsf-2.6.7.dist-info/LICENSE.txt
fdasrsf-2.6.7.dist-info/METADATA
fdasrsf-2.6.7.dist-info/WHEEL
fdasrsf-2.6.7.dist-info/top_level.txt
fdasrsf-2.6.7.dist-info/RECORD
fdasrsf-2.6.7.dist-info/sboms/auditwheel.cdx.json
