Metadata-Version: 2.1
Name: fdasrsf
Version: 2.6.7
Summary: functional data analysis using the square root slope framework
Home-page: http://research.tetonedge.net
Author: J. Derek Tucker
Author-email: "J. Derek Tucker" <jdtuck@sandia.gov>
License: BSD 3-Clause
Project-URL: homepage, http://research.tetonedge.net
Project-URL: repository, https://github.com/jdtuck/fdasrsf_python
Project-URL: documentation, https://fdasrsf-python.readthedocs.io/en/latest/
Keywords: functional data analysis
Classifier: License :: OSI Approved :: BSD License
Classifier: Operating System :: OS Independent
Classifier: Programming Language :: Python
Classifier: Topic :: Scientific/Engineering
Classifier: Topic :: Scientific/Engineering :: Mathematics
Classifier: Programming Language :: Python :: 3
Classifier: Programming Language :: Python :: 3.9
Requires-Python: >=3.10
License-File: LICENSE.txt
Requires-Dist: Cython
Requires-Dist: matplotlib
Requires-Dist: numpy>=1.25
Requires-Dist: scipy>=1.14
Requires-Dist: joblib
Requires-Dist: patsy
Requires-Dist: tqdm
Requires-Dist: six
Requires-Dist: numba
Requires-Dist: cffi>=1.0.0
Requires-Dist: pyparsing
